{
"meta":{"test_sets":[],"test_metrics":[],"learn_metrics":[{"best_value":"Min","name":"MAE"}],"launch_mode":"Train","parameters":"","iteration_count":15,"learn_sets":["learn"],"name":"experiment"},
"iterations":[
{"learn":[7.877279564],"iteration":0,"passed_time":0.05693221772,"remaining_time":0.797051048},
{"learn":[7.599161365],"iteration":1,"passed_time":0.1196203785,"remaining_time":0.7775324603},
{"learn":[7.336681729],"iteration":2,"passed_time":0.180902306,"remaining_time":0.7236092241},
{"learn":[7.148558834],"iteration":3,"passed_time":0.2344296668,"remaining_time":0.6446815838},
{"learn":[6.976225983],"iteration":4,"passed_time":0.2859713477,"remaining_time":0.5719426954},
{"learn":[6.796053305],"iteration":5,"passed_time":0.3309023623,"remaining_time":0.4963535435},
{"learn":[6.588565043],"iteration":6,"passed_time":0.3767038553,"remaining_time":0.4305186917},
{"learn":[6.421310451],"iteration":7,"passed_time":0.4220394013,"remaining_time":0.3692844761},
{"learn":[6.282986848],"iteration":8,"passed_time":0.4726302235,"remaining_time":0.3150868157},
{"learn":[6.113020458],"iteration":9,"passed_time":0.5229976808,"remaining_time":0.2614988404},
{"learn":[6.003931677],"iteration":10,"passed_time":0.57571268,"remaining_time":0.2093500655},
{"learn":[5.863001464],"iteration":11,"passed_time":0.6248690718,"remaining_time":0.1562172679},
{"learn":[5.749936227],"iteration":12,"passed_time":0.6759382334,"remaining_time":0.1039904974},
{"learn":[5.628136478],"iteration":13,"passed_time":0.7253827655,"remaining_time":0.05181305468},
{"learn":[5.544359042],"iteration":14,"passed_time":0.7704092792,"remaining_time":0}
]}